pwfn/__init__.py
pwfn/_orbpowers.py
pwfn/_parser.py
pwfn/py.typed
pwfn-0.1.1.dist-info/LICENSE
pwfn-0.1.1.dist-info/METADATA
pwfn-0.1.1.dist-info/WHEEL
pwfn-0.1.1.dist-info/top_level.txt
pwfn-0.1.1.dist-info/RECORD
