Metadata-Version: 2.1
Name: pwfn
Version: 0.1.1
Summary: pwfn is a single-page library to parse .wfn file
Home-page: https://github.com/clavigne/pwfn
Author: Cyrille Lavigne
Author-email: cyrille.lavigne@mail.utoronto.ca
License: MIT
Keywords: chemistry wfn aimpac qtaim electronic orbitals
Platform: UNKNOWN
Classifier: Development Status :: 3 - Alpha
Classifier: Typing :: Typed
Classifier: License :: OSI Approved :: MIT License
Classifier: Programming Language :: Python :: 3.7
Classifier: Programming Language :: Python :: 3.8
Classifier: Programming Language :: Python :: 3.9
Classifier: Intended Audience :: Science/Research
Classifier: Topic :: Scientific/Engineering :: Chemistry
Classifier: Topic :: Scientific/Engineering :: Physics
Requires-Python: >=3.7
License-File: LICENSE
Requires-Dist: pyparsing
Requires-Dist: numpy
Requires-Dist: importlib-metadata (~=1.0) ; python_version < "3.8"
